{
    "color-red-200": "#EF9A9A",
    "color-red-400": "#EF5350",
    "color-red-800": "#C62828",
    "color-pink-200": "#f48fb1",
    "color-pink-400": "#ec407a",
    "color-pink-800": "#ad1457",
    "color-purple-200": "#ce93d8",
    "color-purple-400": "#ab47bc",
    "color-purple-800": "#6a1b9a",
    "color-deepPurple-200": "#b39ddb",
    "color-deepPurple-400": "#7e57c2",
    "color-deepPurple-800": "#4527a0",
    "color-indigo-200": "#9fa8da",
    "color-indigo-400": "#5c6bc0",
    "color-indigo-800": "#283593",
    "color-blue-200": "#90CAF9",
    "color-blue-400": "#42A5F5",
    "color-blue-800": "#1565C0",
    "color-lightblue-200": "#81D4FA",
    "color-lightblue-400": "#29B6F6",
    "color-lightblue-800": "#0277BD",
    "color-cyan-200": "#80deea",
    "color-cyan-400": "#26c6da",
    "color-cyan-800": "#00838f",
    "color-teal-200": "#80cbc4",
    "color-teal-400": "#26a69a",
    "color-teal-800": "#00695c",
    "color-lightgreen-200": "#C5E1A5",
    "color-lightgreen-400": "#9CCC65",
    "color-lightgreen-800": "#558B2F",
    "color-lime-200": "#E6EE9C",
    "color-lime-400": "#D4E157",
    "color-lime-800": "#9E9D24",
    "color-yellow-200": "#FFF59D",
    "color-yellow-400": "#FFEE58",
    "color-yellow-800": "#F9A825",
    "color-amber-200": "#ffe082",
    "color-amber-400": "#ffca28",
    "color-amber-800": "#ff8f00",
    "color-orange-200": "#FFCC80",
    "color-orange-400": "#FFA726",
    "color-orange-800": "#EF6C00",
    "color-deepOrange-200": "#ffab91",
    "color-deepOrange-400": "#ff7043",
    "color-deepOrange-800": "#d84315",
    "color-grey-200": "#eeeeee",
    "color-grey-400": "#bdbdbd",
    "color-grey-800": "#424242",
    "color-brown-200": "#BCAAA4",
    "color-brown-400": "#8D6E63",
    "color-brown-800": "#4E342E",
    "color-blueGrey-200": "#b0bec5",
    "color-blueGrey-400": "#78909c",
    "color-blueGrey-800": "#37474f"
}